akaraike.py
akaraike-1.0.5.dist-info/METADATA
akaraike-1.0.5.dist-info/WHEEL
akaraike-1.0.5.dist-info/license.txt
akaraike-1.0.5.dist-info/top_level.txt
akaraike-1.0.5.dist-info/RECORD
