Metadata-Version: 2.1
Name: akaraike
Version: 1.0.5
Summary: Generate passwords, API keys of any length and character combination
Home-page: UNKNOWN
License: UNKNOWN
Platform: UNKNOWN
Classifier: Programming Language :: Python :: 3
Classifier: Programming Language :: Python :: 3.7
Classifier: License :: OSI Approved :: MIT License
Classifier: Operating System :: OS Independent
